{
	"schema_version": 1,
	"quilt_loader": {
		"group": "io.github.aelpecyem",
		"id": "la_cucaracha",
		"version": "${version}",
		"metadata": {
			"name": "La Cucaracha",
			"description": "Adds roaches to the game.",
			"contributors": {
				"CyberCat5555": "Owner/Concept/Assets",
				"Aelpecyem": "Developer",
				"Assasingus14": "Sounds"
			},
			"contact": {
				"homepage": "https://github.com/Aelpecyem/la-cucaracha",
				"issues": "https://github.com/Aelpecyem/la-cucaracha/issues",
				"sources": "https://github.com/Aelpecyem/la-cucaracha"
			},
			"icon": "assets/la_cucaracha/icon.png"
		},
		"intermediate_mappings": "net.fabricmc:intermediary",
		"entrypoints": {
			"init": "io.github.aelpecyem.la_cucaracha.LaCucaracha",
			"client_init": "io.github.aelpecyem.la_cucaracha.client.LaCucarachaClient"
		},
		"depends": [
			{
				"id": "quilt_loader",
				"versions": ">=0.17.0-"
			},
			{
				"id": "quilted_fabric_api",
				"versions": ">=4.0.0-"
			},
			{
				"id": "minecraft",
				"versions": ">=1.19.2"
			}
		]
	},
	"mixin": "la_cucaracha.mixins.json"
}
